code_detector/__init__.py
code_detector/detector.py
code_detector/helpers.py
code_detector/utils.py
code_detector-0.1.0.dist-info/LICENSE
code_detector-0.1.0.dist-info/METADATA
code_detector-0.1.0.dist-info/WHEEL
code_detector-0.1.0.dist-info/top_level.txt
code_detector-0.1.0.dist-info/RECORD
