Metadata-Version: 2.1
Name: code-detector
Version: 0.1.0
Summary: A package to detect if text is likely code
Author: Ahmed Zaky
Author-email: ahmedzakymouad303@gmail.com
Keywords: code,detection,text-analysis,regex,nlp
Classifier: Programming Language :: Python :: 3
Classifier: License :: OSI Approved :: MIT License
Classifier: Operating System :: OS Independent
Requires-Python: >=3.6
License-File: LICENSE
